pyxll_dash/__init__.py
pyxll_dash/dash_bridge.py
pyxll_dash/pyxll.py
pyxll_dash-0.0.1.dist-info/licenses/LICENSE.md
pyxll_dash-0.0.1.dist-info/METADATA
pyxll_dash-0.0.1.dist-info/WHEEL
pyxll_dash-0.0.1.dist-info/entry_points.txt
pyxll_dash-0.0.1.dist-info/top_level.txt
pyxll_dash-0.0.1.dist-info/RECORD
