Metadata-Version: 2.4
Name: pyxll-dash
Version: 0.0.1
Summary: Adds Plotly Dash support to PyXLL for integrating Dash apps into Microsoft Excel.
Author-email: Tony Roberts <tony@pyxll.com>
License-Expression: MIT
Project-URL: Repository, https://github.com/pyxll/pyxll-dash
Project-URL: Issues, https://github.com/pyxll/pyxll-dash/issues
Classifier: Programming Language :: Python :: 3
Classifier: Operating System :: Microsoft :: Windows
License-File: LICENSE.md
Requires-Dist: pyxll
Requires-Dist: dash
Requires-Dist: werkzeug
Dynamic: license-file
